api/__init__.py
reactor_cli/main.py
reactor_cli/commands/__init__.py
reactor_cli/commands/capabilities.py
reactor_cli/commands/download.py
reactor_cli/commands/init.py
reactor_cli/commands/run.py
reactor_cli/commands/setup.py
reactor_cli/commands/upload.py
reactor_cli/utils/__init__.py
reactor_cli/utils/config.py
reactor_cli/utils/discovery.py
reactor_cli/utils/runtime.py
reactor_cli/utils/version.py
reactor_cli/utils/weights.py
reactor_runtime/__init__.py
reactor_runtime/context_api.py
reactor_runtime/model_api.py
reactor_runtime/registry.py
reactor_runtime/runtime_api.py
reactor_runtime/output/frame_buffer.py
reactor_runtime/runtimes/headless/headless_runtime.py
reactor_runtime/runtimes/http/http_runtime.py
reactor_runtime/utils/launch.py
reactor_runtime/utils/loader.py
reactor_runtime/utils/messages.py
reactor_runtime/utils/schema.py
reactor_runtime/utils/webrtc.py
template/brightness_example.py
reactor_runtime-1.0.0.dist-info/METADATA
reactor_runtime-1.0.0.dist-info/WHEEL
reactor_runtime-1.0.0.dist-info/entry_points.txt
reactor_runtime-1.0.0.dist-info/top_level.txt
reactor_runtime-1.0.0.dist-info/RECORD
