Metadata-Version: 2.4
Name: reactor_runtime
Version: 1.0.0
Summary: Reactor runtime with public model API
Author-email: Reactor <team@reactor.inc>
Requires-Python: >=3.9
Requires-Dist: websockets>=13.0
Requires-Dist: numpy<2.0
Requires-Dist: pydantic>=2.0.0
Requires-Dist: omegaconf>=2.3.0
Requires-Dist: pyyaml
Requires-Dist: av>=12.0.0
Requires-Dist: aiortc>=1.14.0
Requires-Dist: fastapi>=0.100.0
Requires-Dist: uvicorn[standard]>=0.23.0
Requires-Dist: livekit-api>=1.0.5
Requires-Dist: livekit==1.0.12
Requires-Dist: aiohttp>=3.9.3
Requires-Dist: redis
Requires-Dist: supabase>=2.0.0
Requires-Dist: boto3>=1.28.0
Requires-Dist: opentelemetry-api
Requires-Dist: opentelemetry-sdk
Requires-Dist: opentelemetry-exporter-otlp-proto-http
Requires-Dist: tqdm
Requires-Dist: filelock>=3.12.0
Requires-Dist: grpcio>=1.60.0
